accessmysqlconverter/__init__.py
accessmysqlconverter/accessconnector.py
accessmysqlconverter/accesshandler.py
accessmysqlconverter/application.py
accessmysqlconverter/fileformatter.py
accessmysqlconverter/fileformatterinterface.py
accessmysqlconverter/otherfileformatter.py
accessmysqlconverter/postgresfileformatter.py
accessmysqlconverter/images/hide_pwd.png
accessmysqlconverter/images/icon.ico
accessmysqlconverter/images/watch_pwd.png
accessmysqlconverter-2.0.0.dist-info/LICENSE
accessmysqlconverter-2.0.0.dist-info/METADATA
accessmysqlconverter-2.0.0.dist-info/WHEEL
accessmysqlconverter-2.0.0.dist-info/top_level.txt
accessmysqlconverter-2.0.0.dist-info/RECORD
